MANIFEST.in
README.rst
setup.py
jrc/__init__.py
jrc/cmd.py
jrc/common.py
jrc/compiler.py
jrc/extension.py
jrc/filter.py
jrc/grammar_parse.py
jrc/render.py
jrc.egg-info/PKG-INFO
jrc.egg-info/SOURCES.txt
jrc.egg-info/dependency_links.txt
jrc.egg-info/entry_points.txt
jrc.egg-info/requires.txt
jrc.egg-info/top_level.txt
jrc/parser/__init__.py
jrc/parser/tx/json.tx
jrc/parser/tx/python.tx
test/test_cmd.py
test/test_pipeline.py
test/test_zion.py